[
    {
        "orderNumber": "C0019",
        "content": "居家清潔",
        "orderStatus": "0"
    },
    {
        "orderNumber": "C0123",
        "content": "居家清潔",
        "orderStatus": "0"
    },
    {
        "orderNumber": "C0123",
        "content": "居家清潔",
        "orderStatus": "1"
    },
    {
        "orderNumber": "C0123",
        "content": "居家清潔",
        "orderStatus": "1"
    },
    {
        "orderNumber": "C0123",
        "content": "居家清潔",
        "orderStatus": "1"
    },
    {
        "orderNumber": "C0019",
        "content": "居家清潔",
        "orderStatus": "99"
    }
]